vllm_block/__init__.py
vllm_block/_custom_ops.py
vllm_block/_ipex_ops.py
vllm_block/adapter_commons/__init__.py
vllm_block/adapter_commons/layers.py
vllm_block/adapter_commons/models.py
vllm_block/adapter_commons/request.py
vllm_block/adapter_commons/utils.py
vllm_block/adapter_commons/worker_manager.py
vllm_block/assets/__init__.py
vllm_block/assets/audio.py
vllm_block/assets/base.py
vllm_block/assets/image.py
vllm_block/assets/video.py
vllm_block/attention/__init__.py
vllm_block/attention/backends/__init__.py
vllm_block/attention/backends/abstract.py
vllm_block/attention/backends/blocksparse_attn.py
vllm_block/attention/backends/flash_attn.py
vllm_block/attention/backends/flashinfer.py
vllm_block/attention/backends/flashmla.py
vllm_block/attention/backends/hpu_attn.py
vllm_block/attention/backends/ipex_attn.py
vllm_block/attention/backends/mla/__init__.py
vllm_block/attention/backends/mla/common.py
vllm_block/attention/backends/pallas.py
vllm_block/attention/backends/placeholder_attn.py
vllm_block/attention/backends/rocm_flash_attn.py
vllm_block/attention/backends/torch_sdpa.py
vllm_block/attention/backends/triton_mla.py
vllm_block/attention/backends/utils.py
vllm_block/attention/backends/xformers.py
vllm_block/attention/layer.py
vllm_block/attention/ops/__init__.py
vllm_block/attention/ops/blocksparse_attention/__init__.py
vllm_block/attention/ops/blocksparse_attention/blocksparse_attention_kernel.py
vllm_block/attention/ops/blocksparse_attention/interface.py
vllm_block/attention/ops/blocksparse_attention/utils.py
vllm_block/attention/ops/chunked_prefill_paged_decode.py
vllm_block/attention/ops/flashmla.py
vllm_block/attention/ops/hpu_paged_attn.py
vllm_block/attention/ops/ipex_attn.py
vllm_block/attention/ops/nki_flash_attn.py
vllm_block/attention/ops/paged_attn.py
vllm_block/attention/ops/prefix_prefill.py
vllm_block/attention/ops/triton_decode_attention.py
vllm_block/attention/ops/triton_flash_attention.py
vllm_block/attention/ops/triton_merge_attn_states.py
vllm_block-0.1.0.dist-info/LICENSE
vllm_block-0.1.0.dist-info/WHEEL
vllm_block-0.1.0.dist-info/METADATA
vllm_block-0.1.0.dist-info/RECORD
